p1_helpers/__init__.py
p1_helpers/dbg.py
p1_helpers/io_.py
p1_helpers/parser.py
p1_helpers/printing.py
p1_helpers/s3.py
p1_helpers/system_interaction.py
p1_helpers-1.0.0.dist-info/METADATA
p1_helpers-1.0.0.dist-info/WHEEL
p1_helpers-1.0.0.dist-info/top_level.txt
p1_helpers-1.0.0.dist-info/RECORD
