Metadata-Version: 2.1
Name: p1-helpers
Version: 1.0.0
Summary: A corporate helper package
Home-page: https://github.com/ParticleDev/p1_helpers
Author: ParticleOne Team
Author-email: malanin@particle.one
Maintainer: 
Maintainer-email: 
License: MIT
Keywords: p1_helpers,particle,particleone,particle.one
Platform: UNKNOWN
Classifier: Intended Audience :: Developers
Classifier: License :: OSI Approved :: MIT License
Classifier: Operating System :: Unix
Classifier: Programming Language :: Python :: 3.7
Classifier: Programming Language :: Python :: 3.8
Classifier: Programming Language :: Python :: 3.9
Requires-Python: >= 3.7
Requires-Dist: pandas (>=1.1.1)
Requires-Dist: boto3 (>=1.14.51)
Requires-Dist: tqdm (>=4.61.2)
